{
  "level_number": 157,
  "name": "Level 157",
  "difficulty": 7,
  "alien_groups": [
    {
      "alien_type": "alien_22_large_01",
      "count": 20,
      "formation": "circle",
      "spacing": 17.6,
      "entry_point": "right_top",
      "path": [
        {
          "x": 0.9,
          "y": 0.1,
          "wait_time": 0,
          "shoot": false
        },
        {
          "x": 0.8032968716892838,
          "y": 0.33562413647913314,
          "wait_time": 1.4754361395682967,
          "shoot": true
        },
        {
          "x": 0.5048956109038988,
          "y": 0.5827830222049475,
          "wait_time": 0.5569868615059593,
          "shoot": true
        },
        {
          "x": 0.6752363345311099,
          "y": 0.1,
          "wait_time": 0,
          "shoot": false
        }
      ],
      "movement_pattern": "circular",
      "speed": 2.1735164774699385,
      "health": 7,
      "shoot_interval": 1.9118392206471813,
      "group_behavior": true
    },
    {
      "alien_type": "alien_23_small_02",
      "count": 29,
      "formation": "circle",
      "spacing": 17.6,
      "entry_point": "top_right",
      "path": [
        {
          "x": 0.8,
          "y": 0.1,
          "wait_time": 0,
          "shoot": false
        },
        {
          "x": 0.463237297409792,
          "y": 0.3649234248027141,
          "wait_time": 1.0596553632284504,
          "shoot": true
        },
        {
          "x": 0.482310139956031,
          "y": 0.25575383538551205,
          "wait_time": 0.6676735653263637,
          "shoot": true
        },
        {
          "x": 0.6287311445395597,
          "y": 0.2651244812350123,
          "wait_time": 1.4177134674899299,
          "shoot": true
        },
        {
          "x": 0.6685519707757992,
          "y": 0.1,
          "wait_time": 0,
          "shoot": false
        }
      ],
      "movement_pattern": "zigzag",
      "speed": 1.5655506829445152,
      "health": 1,
      "shoot_interval": 2.960726736312721,
      "group_behavior": true
    },
    {
      "alien_type": "alien_25_small_02",
      "count": 22,
      "formation": "star",
      "spacing": 17.6,
      "entry_point": "top_right",
      "path": [
        {
          "x": 0.8,
          "y": 0.1,
          "wait_time": 0,
          "shoot": false
        },
        {
          "x": 0.41648933093955876,
          "y": 0.5920984013596127,
          "wait_time": 1.9420026341333718,
          "shoot": false
        },
        {
          "x": 0.701959305336072,
          "y": 0.1,
          "wait_time": 0,
          "shoot": false
        }
      ],
      "movement_pattern": "zigzag",
      "speed": 1.6432870444847083,
      "health": 7,
      "shoot_interval": 2.1453031510416207,
      "group_behavior": true
    },
    {
      "alien_type": "alien_24_small_01",
      "count": 25,
      "formation": "wave",
      "spacing": 14.4,
      "entry_point": "top_left",
      "path": [
        {
          "x": 0.2,
          "y": 0.1,
          "wait_time": 0,
          "shoot": false
        },
        {
          "x": 0.6703978309608433,
          "y": 0.41270788345265186,
          "wait_time": 0.567751964145832,
          "shoot": true
        },
        {
          "x": 0.8833020923449539,
          "y": 0.536244690504784,
          "wait_time": 1.1393960030341026,
          "shoot": true
        },
        {
          "x": 0.41865566523264985,
          "y": 0.5329940523275476,
          "wait_time": 1.8922919049976246,
          "shoot": false
        },
        {
          "x": 0.23425225231099708,
          "y": 0.1,
          "wait_time": 0,
          "shoot": false
        }
      ],
      "movement_pattern": "straight",
      "speed": 1.865468747777412,
      "health": 7,
      "shoot_interval": 2.329540703150533,
      "group_behavior": false
    },
    {
      "alien_type": "alien_23_large_02",
      "count": 24,
      "formation": "circle",
      "spacing": 17.6,
      "entry_point": "right_top",
      "path": [
        {
          "x": 0.9,
          "y": 0.1,
          "wait_time": 0,
          "shoot": false
        },
        {
          "x": 0.5080137104565426,
          "y": 0.3276063840488455,
          "wait_time": 1.5009041006914479,
          "shoot": false
        },
        {
          "x": 0.6432203502077971,
          "y": 0.5608488548492641,
          "wait_time": 0.8764191838396849,
          "shoot": true
        },
        {
          "x": 0.7923830855319228,
          "y": 0.21969219265761636,
          "wait_time": 1.1603764673908403,
          "shoot": false
        },
        {
          "x": 0.6932945513106351,
          "y": 0.2951074201660168,
          "wait_time": 1.7444529103224249,
          "shoot": false
        },
        {
          "x": 0.15931400441372576,
          "y": 0.5581398340294061,
          "wait_time": 1.3911119453784002,
          "shoot": false
        },
        {
          "x": 0.6377335274266537,
          "y": 0.4337323862726986,
          "wait_time": 1.9709223041399577,
          "shoot": false
        },
        {
          "x": 0.8286557367610786,
          "y": 0.23875568979246295,
          "wait_time": 1.6628833385526112,
          "shoot": false
        },
        {
          "x": 0.38975091738038664,
          "y": 0.1,
          "wait_time": 0,
          "shoot": false
        }
      ],
      "movement_pattern": "zigzag",
      "speed": 2.3007976923161824,
      "health": 3,
      "shoot_interval": 2.6399913796183654,
      "group_behavior": false
    },
    {
      "alien_type": "alien_24_small_01",
      "count": 29,
      "formation": "line",
      "spacing": 16.0,
      "entry_point": "top_left",
      "path": [
        {
          "x": 0.2,
          "y": 0.1,
          "wait_time": 0,
          "shoot": false
        },
        {
          "x": 0.27559860106877904,
          "y": 0.5522076832128113,
          "wait_time": 0.9523043833028031,
          "shoot": false
        },
        {
          "x": 0.2806900332594857,
          "y": 0.1,
          "wait_time": 0,
          "shoot": false
        }
      ],
      "movement_pattern": "straight",
      "speed": 2.234602045818136,
      "health": 7,
      "shoot_interval": 2.335229505469063,
      "group_behavior": false
    },
    {
      "alien_type": "alien_23_small_02",
      "count": 27,
      "formation": "star",
      "spacing": 17.6,
      "entry_point": "top_left",
      "path": [
        {
          "x": 0.2,
          "y": 0.1,
          "wait_time": 0,
          "shoot": false
        },
        {
          "x": 0.2045281293754184,
          "y": 0.4008987006889799,
          "wait_time": 0.9044942151461685,
          "shoot": false
        },
        {
          "x": 0.31321791697463186,
          "y": 0.4777030467449666,
          "wait_time": 0.94140647502584,
          "shoot": false
        },
        {
          "x": 0.6764816145936577,
          "y": 0.2574307058179251,
          "wait_time": 1.1964868886067554,
          "shoot": true
        },
        {
          "x": 0.2869136700187832,
          "y": 0.20179612123177526,
          "wait_time": 1.7264659221882095,
          "shoot": true
        },
        {
          "x": 0.6980989363385801,
          "y": 0.3920546984484401,
          "wait_time": 1.3910237807506454,
          "shoot": true
        },
        {
          "x": 0.3560896357762021,
          "y": 0.5258163831886846,
          "wait_time": 0.9436664598227522,
          "shoot": false
        },
        {
          "x": 0.42423673329619993,
          "y": 0.25843721100712563,
          "wait_time": 1.7193277667592797,
          "shoot": false
        },
        {
          "x": 0.31427529706588475,
          "y": 0.1,
          "wait_time": 0,
          "shoot": false
        }
      ],
      "movement_pattern": "teleport",
      "speed": 2.2388527882885545,
      "health": 6,
      "shoot_interval": 2.001733630769747,
      "group_behavior": true
    }
  ],
  "boss_data": null,
  "background_speed": 2.2,
  "music_track": "level7.mp3",
  "special_effects": [],
  "power_up_frequency": 0.2,
  "minimum_clear_time": 30.0
}