{
  "level_number": 184,
  "name": "Level 184",
  "difficulty": 7,
  "alien_groups": [
    {
      "alien_type": "alien_22_small_02",
      "count": 22,
      "formation": "circle",
      "spacing": 44,
      "entry_point": "top_center",
      "path": [
        {
          "x": 0.5,
          "y": 0.1,
          "wait_time": 0,
          "shoot": false
        },
        {
          "x": 0.7722260082285171,
          "y": 0.4709877660228945,
          "wait_time": 1.5116866222794043,
          "shoot": false
        },
        {
          "x": 0.5023864145014101,
          "y": 0.23713573945086874,
          "wait_time": 1.3100936697177161,
          "shoot": true
        },
        {
          "x": 0.7567175300119352,
          "y": 0.3743910770855947,
          "wait_time": 1.8774830419110642,
          "shoot": true
        },
        {
          "x": 0.44047447720873845,
          "y": 0.252406359141069,
          "wait_time": 0.7898187006650581,
          "shoot": false
        },
        {
          "x": 0.15664214757575234,
          "y": 0.3858138666101313,
          "wait_time": 0.6840294115405441,
          "shoot": false
        },
        {
          "x": 0.8725873624312286,
          "y": 0.5711999082046695,
          "wait_time": 0.8310313807444408,
          "shoot": false
        },
        {
          "x": 0.7215756119121679,
          "y": 0.1,
          "wait_time": 0,
          "shoot": false
        }
      ],
      "movement_pattern": "zigzag",
      "speed": 2.3043113068579744,
      "health": 5,
      "shoot_interval": 2.979838042342942,
      "group_behavior": true
    },
    {
      "alien_type": "alien_24_large_01",
      "count": 25,
      "formation": "cross",
      "spacing": 52,
      "entry_point": "top_left",
      "path": [
        {
          "x": 0.2,
          "y": 0.1,
          "wait_time": 0,
          "shoot": false
        },
        {
          "x": 0.17693446683579428,
          "y": 0.3704717836950485,
          "wait_time": 1.5262767026033053,
          "shoot": false
        },
        {
          "x": 0.682363694321075,
          "y": 0.2327051538803463,
          "wait_time": 0.5519893335373105,
          "shoot": false
        },
        {
          "x": 0.7591058021780842,
          "y": 0.3548221057048058,
          "wait_time": 1.7748653791565465,
          "shoot": true
        },
        {
          "x": 0.6989097187343511,
          "y": 0.4083514671253108,
          "wait_time": 1.521232583105511,
          "shoot": true
        },
        {
          "x": 0.7667952140447525,
          "y": 0.1,
          "wait_time": 0,
          "shoot": false
        }
      ],
      "movement_pattern": "wave",
      "speed": 1.7748716149826094,
      "health": 7,
      "shoot_interval": 1.8631227114294526,
      "group_behavior": true
    },
    {
      "alien_type": "alien_23_large_02",
      "count": 28,
      "formation": "circle",
      "spacing": 52,
      "entry_point": "right_top",
      "path": [
        {
          "x": 0.9,
          "y": 0.1,
          "wait_time": 0,
          "shoot": false
        },
        {
          "x": 0.3564467545181005,
          "y": 0.44524179720076384,
          "wait_time": 1.2966423731515477,
          "shoot": true
        },
        {
          "x": 0.3073773765152291,
          "y": 0.1,
          "wait_time": 0,
          "shoot": false
        }
      ],
      "movement_pattern": "zigzag",
      "speed": 2.312692199251904,
      "health": 4,
      "shoot_interval": 2.2754651339974012,
      "group_behavior": false
    },
    {
      "alien_type": "alien_24_large_01",
      "count": 28,
      "formation": "v",
      "spacing": 44,
      "entry_point": "top_right",
      "path": [
        {
          "x": 0.8,
          "y": 0.1,
          "wait_time": 0,
          "shoot": false
        },
        {
          "x": 0.28533329234691723,
          "y": 0.3253082681333327,
          "wait_time": 1.157670315102192,
          "shoot": true
        },
        {
          "x": 0.5101990225017373,
          "y": 0.36742455211408437,
          "wait_time": 0.7929422883250103,
          "shoot": false
        },
        {
          "x": 0.15466285767010224,
          "y": 0.47303829139667886,
          "wait_time": 1.1029080427174123,
          "shoot": true
        },
        {
          "x": 0.47767625183107826,
          "y": 0.1,
          "wait_time": 0,
          "shoot": false
        }
      ],
      "movement_pattern": "zigzag",
      "speed": 2.323249068221817,
      "health": 1,
      "shoot_interval": 1.5074618244905729,
      "group_behavior": false
    },
    {
      "alien_type": "alien_25_large_01",
      "count": 25,
      "formation": "circle",
      "spacing": 52,
      "entry_point": "top_center",
      "path": [
        {
          "x": 0.5,
          "y": 0.1,
          "wait_time": 0,
          "shoot": false
        },
        {
          "x": 0.816695964051909,
          "y": 0.5269053785822573,
          "wait_time": 1.3210470748481462,
          "shoot": false
        },
        {
          "x": 0.6485352134118829,
          "y": 0.2119513294116304,
          "wait_time": 1.617630734687942,
          "shoot": false
        },
        {
          "x": 0.7509650739440936,
          "y": 0.36979803458630245,
          "wait_time": 0.6932745630114429,
          "shoot": true
        },
        {
          "x": 0.2620420682301952,
          "y": 0.5255632345143924,
          "wait_time": 1.2367951963776727,
          "shoot": true
        },
        {
          "x": 0.6751998852515173,
          "y": 0.1,
          "wait_time": 0,
          "shoot": false
        }
      ],
      "movement_pattern": "wave",
      "speed": 2.0893961109678427,
      "health": 3,
      "shoot_interval": 1.638738832518759,
      "group_behavior": false
    },
    {
      "alien_type": "alien_25_large_02",
      "count": 21,
      "formation": "star",
      "spacing": 52,
      "entry_point": "top_center",
      "path": [
        {
          "x": 0.5,
          "y": 0.1,
          "wait_time": 0,
          "shoot": false
        },
        {
          "x": 0.5146203488480555,
          "y": 0.31717555636070605,
          "wait_time": 0.6887723954482408,
          "shoot": false
        },
        {
          "x": 0.21167917516235246,
          "y": 0.5706206009971295,
          "wait_time": 1.0583972889297768,
          "shoot": true
        },
        {
          "x": 0.4088041153341502,
          "y": 0.2534176607992295,
          "wait_time": 1.2027092968087396,
          "shoot": false
        },
        {
          "x": 0.6516455249365524,
          "y": 0.534594530037625,
          "wait_time": 1.4095496501644516,
          "shoot": false
        },
        {
          "x": 0.5910702789906197,
          "y": 0.337090656839391,
          "wait_time": 0.8237499103382956,
          "shoot": true
        },
        {
          "x": 0.4581336177701605,
          "y": 0.4519518781601646,
          "wait_time": 1.133369309083833,
          "shoot": false
        },
        {
          "x": 0.550172533525314,
          "y": 0.33322808403113047,
          "wait_time": 1.9317648167385502,
          "shoot": false
        },
        {
          "x": 0.27014491637171234,
          "y": 0.43450234421797934,
          "wait_time": 0.9839050061883992,
          "shoot": true
        },
        {
          "x": 0.3066302646331279,
          "y": 0.3842234665301699,
          "wait_time": 0.9309848952997639,
          "shoot": true
        },
        {
          "x": 0.29293035837178283,
          "y": 0.21912243410208704,
          "wait_time": 1.7783492616350443,
          "shoot": true
        },
        {
          "x": 0.46996712461237783,
          "y": 0.1,
          "wait_time": 0,
          "shoot": false
        }
      ],
      "movement_pattern": "circular",
      "speed": 1.9958571348870089,
      "health": 7,
      "shoot_interval": 2.154538026294297,
      "group_behavior": false
    },
    {
      "alien_type": "alien_22_small_01",
      "count": 24,
      "formation": "star",
      "spacing": 45,
      "entry_point": "left_top",
      "path": [
        {
          "x": 0.1,
          "y": 0.1,
          "wait_time": 0,
          "shoot": false
        },
        {
          "x": 0.7077990637798741,
          "y": 0.3628349579606672,
          "wait_time": 0.5391498841993858,
          "shoot": false
        },
        {
          "x": 0.5487873727637476,
          "y": 0.31333605433884404,
          "wait_time": 1.9890859116479924,
          "shoot": true
        },
        {
          "x": 0.6777300523082727,
          "y": 0.5531325484583081,
          "wait_time": 1.6123729369338116,
          "shoot": false
        },
        {
          "x": 0.529448697396526,
          "y": 0.5974039811750912,
          "wait_time": 1.8384247969738232,
          "shoot": true
        },
        {
          "x": 0.28508665887930806,
          "y": 0.1,
          "wait_time": 0,
          "shoot": false
        }
      ],
      "movement_pattern": "circular",
      "speed": 1.791329591027779,
      "health": 5,
      "shoot_interval": 2.566268716424901,
      "group_behavior": false
    },
    {
      "alien_type": "alien_25_small_02",
      "count": 21,
      "formation": "star",
      "spacing": 51,
      "entry_point": "right_top",
      "path": [
        {
          "x": 0.9,
          "y": 0.1,
          "wait_time": 0,
          "shoot": false
        },
        {
          "x": 0.22490381540488996,
          "y": 0.34094544360210277,
          "wait_time": 0.821789591272508,
          "shoot": false
        },
        {
          "x": 0.3954176137173362,
          "y": 0.31316695110253945,
          "wait_time": 0.9702516486590221,
          "shoot": false
        },
        {
          "x": 0.6317706638751015,
          "y": 0.5418564411529647,
          "wait_time": 1.4109754990704704,
          "shoot": true
        },
        {
          "x": 0.6517291784467589,
          "y": 0.21159427252380497,
          "wait_time": 1.9015437795347538,
          "shoot": false
        },
        {
          "x": 0.4442541257473902,
          "y": 0.5267536465271876,
          "wait_time": 0.5716240619873338,
          "shoot": false
        },
        {
          "x": 0.8021855163464121,
          "y": 0.2417090072562137,
          "wait_time": 1.1962311084687407,
          "shoot": false
        },
        {
          "x": 0.6718344293827841,
          "y": 0.44932275316413584,
          "wait_time": 1.2521335168014502,
          "shoot": false
        },
        {
          "x": 0.8986868953691681,
          "y": 0.2846149032861943,
          "wait_time": 1.7646503416288812,
          "shoot": true
        },
        {
          "x": 0.2467787710324701,
          "y": 0.4776646266704212,
          "wait_time": 1.376223705468326,
          "shoot": true
        },
        {
          "x": 0.21416513306465765,
          "y": 0.1,
          "wait_time": 0,
          "shoot": false
        }
      ],
      "movement_pattern": "swarm",
      "speed": 2.178888285221348,
      "health": 1,
      "shoot_interval": 1.675940173186429,
      "group_behavior": true
    }
  ],
  "boss_data": null,
  "background_speed": 2.4000000000000004,
  "music_track": "level8.mp3",
  "special_effects": [],
  "power_up_frequency": 0.2,
  "minimum_clear_time": 30.0
}